{
	"configurations" : 
	[
		{
			"directories" : 
			[
				{
					"build" : ".",
					"hasInstallRule" : true,
					"minimumCMakeVersion" : 
					{
						"string" : "3.5"
					},
					"projectIndex" : 0,
					"source" : ".",
					"targetIndexes" : 
					[
						0,
						1
					]
				}
			],
			"name" : "Debug",
			"projects" : 
			[
				{
					"directoryIndexes" : 
					[
						0
					],
					"name" : "proj7",
					"targetIndexes" : 
					[
						0,
						1
					]
				}
			],
			"targets" : 
			[
				{
					"directoryIndex" : 0,
					"id" : "MyString::@6890427a1f51a3e7e1df",
					"jsonFile" : "target-MyString-Debug-d2db82d60d008e6015b0.json",
					"name" : "MyString",
					"projectIndex" : 0
				},
				{
					"directoryIndex" : 0,
					"id" : "proj7::@6890427a1f51a3e7e1df",
					"jsonFile" : "target-proj7-Debug-d2817886666e14ecaa2d.json",
					"name" : "proj7",
					"projectIndex" : 0
				}
			]
		}
	],
	"kind" : "codemodel",
	"paths" : 
	{
		"build" : "D:/qt/PROJECTS/learning/project 7/project7/build",
		"source" : "D:/qt/PROJECTS/learning/project 7/project7"
	},
	"version" : 
	{
		"major" : 2,
		"minor" : 0
	}
}
